mcnets/__deprecated.py
mcnets/__init__.py
mcnets/_experimental.py
mcnets/activations.py
mcnets/main.py
mcnets/tools.py
mcnets-2.0.7.dist-info/METADATA
mcnets-2.0.7.dist-info/WHEEL
mcnets-2.0.7.dist-info/licenses/LICENSE
mcnets-2.0.7.dist-info/RECORD
