Metadata-Version: 2.3
Name: mcnets
Version: 2.0.7
Summary: Lightweight Machine Learning package with models that train using simple Monte Carlo-like methods.
Project-URL: Homepage, https://github.com/SciCapt/Monte-Carlo-Neural-Nets
Project-URL: Bug Tracker, https://github.com/SciCapt/Monte-Carlo-Neural-Nets/issues
Author-email: Sean <svs.2k15@gmail.com>
License-File: LICENSE
Classifier: License :: OSI Approved :: MIT License
Classifier: Operating System :: OS Independent
Classifier: Programming Language :: Python :: 3
Requires-Python: >=3.7
